instagram_private_api_extensions/__init__.py
instagram_private_api_extensions/compat.py
instagram_private_api_extensions/live.py
instagram_private_api_extensions/media.py
instagram_private_api_extensions/pagination.py
instagram_private_api_extensions/replay.py
instagram_private_api_extensions-0.3.8.dist-info/LICENSE
instagram_private_api_extensions-0.3.8.dist-info/METADATA
instagram_private_api_extensions-0.3.8.dist-info/WHEEL
instagram_private_api_extensions-0.3.8.dist-info/top_level.txt
instagram_private_api_extensions-0.3.8.dist-info/RECORD
