Metadata-Version: 2.1
Name: instagram_private_api_extensions
Version: 0.3.8
Summary: An extension module for https://github.com/ping/instagram_private_api
Home-page: https://github.com/ping/instagram_private_api_extensions/tree/master
Author: ping
Author-email: lastmodified@gmail.com
License: MIT
Keywords: instagram private api extensions
Platform: UNKNOWN
Classifier: Development Status :: 4 - Beta
Classifier: Intended Audience :: Developers
Classifier: License :: OSI Approved :: MIT License
Classifier: Topic :: Software Development :: Libraries :: Python Modules
Classifier: Programming Language :: Python :: 2.7
Classifier: Programming Language :: Python :: 3.5
